bopt/__init__.py
bopt/basic_types.py
bopt/experiment.py
bopt/gp_config.py
bopt/hyperparam_values.py
bopt/plot.py
bopt/sample.py
bopt/acquisition_functions/__init__.py
bopt/acquisition_functions/acquisition_functions.py
bopt/cli/__init__.py
bopt/cli/clean.py
bopt/cli/cli.py
bopt/cli/debug.py
bopt/cli/exp.py
bopt/cli/init.py
bopt/cli/jobstat.py
bopt/cli/manual_run.py
bopt/cli/plot.py
bopt/cli/run.py
bopt/cli/run_single.py
bopt/cli/suggest.py
bopt/cli/util.py
bopt/cli/web.py
bopt/models/__init__.py
bopt/models/gpy_model.py
bopt/models/model.py
bopt/models/parameters.py
bopt/models/random_search.py
bopt/runner/__init__.py
bopt/runner/abstract.py
bopt/runner/job_loader.py
bopt/runner/local_runner.py
bopt/runner/runner_loader.py
bopt/runner/sge_runner.py
bopt/templates/__init__.py
bopt/templates/index.html
bopt/templates/old_index.html
bopt-0.1.0.dist-info/DESCRIPTION.rst
bopt-0.1.0.dist-info/METADATA
bopt-0.1.0.dist-info/RECORD
bopt-0.1.0.dist-info/WHEEL
bopt-0.1.0.dist-info/entry_points.txt
bopt-0.1.0.dist-info/metadata.json
bopt-0.1.0.dist-info/top_level.txt
tests/__init__.py
tests/opt_functions.py
tests/test_todict_fromdict.py
